README.md
setup.py
Mess_Client_al.egg-info/PKG-INFO
Mess_Client_al.egg-info/SOURCES.txt
Mess_Client_al.egg-info/dependency_links.txt
Mess_Client_al.egg-info/requires.txt
Mess_Client_al.egg-info/top_level.txt
client/__init__.py
client/client.py
client/clientapp/__init__.py
client/clientapp/client_chat_window.py
client/clientapp/client_gui_chat_window.py
client/clientapp/client_gui_login.py
client/clientapp/database_client.py
client/clientapp/decorators.py
client/clientapp/metaclss_client.py
client/config/__init__.py
client/config/settings.py
client/config/utils.py
client/logs/__init__.py
client/logs/client_log_config.py
client/unittests/__init__.py
client/unittests/test_utils.py