Metadata-Version: 1.0
Name: Mess-Client-al
Version: 0.0.1
Summary: Messenger_Client
Home-page: UNKNOWN
Author: Alena Vetrova
Author-email: geekbr.alena.vetr@gmail.com
License: UNKNOWN
Platform: UNKNOWN
